{
  "_comment": "Compact default layout for 13-16 inch screens",
  "window": {
    "width": 1100,
    "height": 900,
    "min_width": 760,
    "min_height": 620
  },
  "config_panel": {
    "prompt_preview_height": 6,
    "prompt_preview_font_size": 8,
    "negative_prompt_height": 1,
    "prompt_preview_width": 0,
    "prompt_preview_right_pad": 20,
    "prompt_preview_offset_x": 12
  },
  "drop_zone": {
    "height": 500
  },
  "queue_panel": {
    "width": 320
  },
  "history_panel": {
    "height": 180,
    "visible_rows": 6
  },
  "debug": {
    "enabled": false,
    "inspector_hotkey": "F12",
    "reload_hotkey": "F5"
  },
  "sash_positions": {
    "dropzone": [
      1,
      500
    ],
    "queue": [
      320,
      1
    ],
    "log": [
      1,
      150
    ]
  }
}
